arguspy/__init__.py
arguspy/ftp_ftplib.py
arguspy/http_requests.py
arguspy/mssql_pymssql.py
arguspy/mysql_pymysql.py
arguspy/snmp_pysnmp.py
arguspy/ssh_paramiko.py
arguspy/winrm_pywinrm.py
arguspy/wmi_subprocess.py
arguspy-2.0.0.dist-info/DESCRIPTION.rst
arguspy-2.0.0.dist-info/METADATA
arguspy-2.0.0.dist-info/RECORD
arguspy-2.0.0.dist-info/WHEEL
arguspy-2.0.0.dist-info/metadata.json
arguspy-2.0.0.dist-info/top_level.txt
tests/__init__.py
tests/test_ftp.py
