Metadata-Version: 2.0
Name: arguspy
Version: 2.0.0
Summary: Common interface of tons protocals, used for monitoring tools, like nagios/icinga...
Home-page: https://github.com/crazy-canux/arguspy
Author: Canux CHENG
Author-email: canuxcheng@gmail.com
License: GPL
Keywords: monitoring nagios icinga plugins
Platform: any
Classifier: Development Status :: 5 - Production/Stable
Classifier: Environment :: Plugins
Classifier: Intended Audience :: Developers
Classifier: Natural Language :: English
Classifier: License :: OSI Approved :: GNU General Public License (GPL)
Classifier: Operating System :: POSIX
Classifier: Programming Language :: Python
Classifier: Programming Language :: Python :: 2.7
Classifier: Topic :: System :: Monitoring
